trodes_to_nwb/__init__.py
trodes_to_nwb/_version.py
trodes_to_nwb/convert.py
trodes_to_nwb/convert_analog.py
trodes_to_nwb/convert_dios.py
trodes_to_nwb/convert_ephys.py
trodes_to_nwb/convert_intervals.py
trodes_to_nwb/convert_optogenetics.py
trodes_to_nwb/convert_position.py
trodes_to_nwb/convert_rec_header.py
trodes_to_nwb/convert_yaml.py
trodes_to_nwb/data_scanner.py
trodes_to_nwb/metadata_validation.py
trodes_to_nwb/nwb_schema.json
trodes_to_nwb/spike_gadgets_raw_io.py
trodes_to_nwb/device_metadata/optical_fiber_metadata/demo_fiber_device_1.yml
trodes_to_nwb/device_metadata/optical_fiber_metadata/optogenix_lambda_fiber.yml
trodes_to_nwb/device_metadata/optical_source_metadata/demo_source_1.yml
trodes_to_nwb/device_metadata/optical_source_metadata/luxX_638_200.yml
trodes_to_nwb/device_metadata/probe_metadata/128c-4s4mm6cm-20um-40um-sl.yml
trodes_to_nwb/device_metadata/probe_metadata/128c-4s6mm6cm-15um-26um-sl.yml
trodes_to_nwb/device_metadata/probe_metadata/128c-4s8mm6cm-20um-40um-sl.yml
trodes_to_nwb/device_metadata/probe_metadata/32c-2s8mm6cm-20um-40um-dl.yml
trodes_to_nwb/device_metadata/probe_metadata/64c-3s6mm6cm-20um-40um-sl.yml
trodes_to_nwb/device_metadata/probe_metadata/64c-4s6mm6cm-20um-40um-dl.yml
trodes_to_nwb/device_metadata/probe_metadata/A1x32-6mm-50-177-H32_21mm.yml
trodes_to_nwb/device_metadata/probe_metadata/NET-EBL-128ch-single-shank.yml
trodes_to_nwb/device_metadata/probe_metadata/tetrode_12.5.yml
trodes_to_nwb/device_metadata/virus_metadata/AAV-1-Ef1a-DIO-ChRmine-mScarlet.yml
trodes_to_nwb/device_metadata/virus_metadata/AAV-8-Ef1a-DIO-ChRmine-mScarlet.yml
trodes_to_nwb/device_metadata/virus_metadata/demo_virus_1.yml
trodes_to_nwb/tests/__init__.py
trodes_to_nwb/tests/test_behavior_only_rec.py
trodes_to_nwb/tests/test_convert.py
trodes_to_nwb/tests/test_convert_analog.py
trodes_to_nwb/tests/test_convert_dios.py
trodes_to_nwb/tests/test_convert_ephys.py
trodes_to_nwb/tests/test_convert_intervals.py
trodes_to_nwb-0.1.9.dist-info/METADATA
trodes_to_nwb-0.1.9.dist-info/WHEEL
trodes_to_nwb-0.1.9.dist-info/licenses/LICENSE
trodes_to_nwb-0.1.9.dist-info/RECORD
