Metadata-Version: 2.4
Name: trodes_to_nwb
Version: 0.1.9
Summary: A python package to convert SpikeGadgets data to NWB
Project-URL: Homepage, https://github.com/LorenFrankLab/trodes_to_nwb
Project-URL: Bug Tracker, https://github.com/LorenFrankLab/trodes_to_nwb/issues
Author-email: Sam Bray <sam.bray@ucsf.edu>, Eric Denovellis <eric.denovellis@ucsf.edu>, Ryan Ly <rly@lbl.gov>, Philip Adenekan <phil.adenekan@ucsf.edu>, Loren Frank <loren.frank@ucsf.edu>
License: MIT License
License-File: LICENSE
Classifier: License :: OSI Approved :: MIT License
Classifier: Operating System :: OS Independent
Classifier: Programming Language :: Python :: 3
Requires-Python: >=3.8
Requires-Dist: dask[complete]
Requires-Dist: ffmpeg
Requires-Dist: jsonschema<4.21.0
Requires-Dist: ndx-franklab-novela
Requires-Dist: neo>=0.13.4
Requires-Dist: numpy
Requires-Dist: nwbinspector>=0.5.0
Requires-Dist: pandas
Requires-Dist: pynwb<=3.0.0
Requires-Dist: pyyaml
Requires-Dist: scipy
Provides-Extra: test
Requires-Dist: black; extra == 'test'
Requires-Dist: pytest; extra == 'test'
Requires-Dist: pytest-cov; extra == 'test'
Requires-Dist: pytest-mock; extra == 'test'
